uiside/__init__.py
uiside/dialogs/__init__.py
uiside/dialogs/common.py
uiside/dialogs/file.py
uiside/dialogs/msg.py
uiside-0.1.2.dist-info/METADATA
uiside-0.1.2.dist-info/RECORD
uiside-0.1.2.dist-info/WHEEL
uiside-0.1.2.dist-info/top_level.txt
