Metadata-Version: 2.1
Name: uiside
Version: 0.1.2
Summary: Additional UI components for PySide-based applications
Home-page: https://gitlab.com/ykh/uiside
Author: Confluenity
Author-email: UNKNOWN
License: MIT
Keywords: pyside ui components
Platform: UNKNOWN
Classifier: Development Status :: 3 - Alpha
Classifier: Intended Audience :: Developers
Classifier: License :: OSI Approved :: MIT License
Classifier: Programming Language :: Python :: 2
Classifier: Programming Language :: Python :: 2.7
